MANIFEST.in
README.rst
setup.py
geoindex/__init__.py
geoindex/geo_grid_index.py
geoindex/geo_point.py
geoindex/utils.py
geoindex.egg-info/PKG-INFO
geoindex.egg-info/SOURCES.txt
geoindex.egg-info/dependency_links.txt
geoindex.egg-info/requires.txt
geoindex.egg-info/top_level.txt