Metadata-Version: 1.1
Name: geoindex
Version: 0.0.1
Summary: Simple library for perform quick nearby search for geo spatial data.
Home-page: http://github.com/gusdan/geoindex
Author: Danil Gusev
Author-email: gusev.danil@gmail.com
License: BSD License
Keywords: geo index spatial geohash indexer grid
Platform: any
Classifier: Development Status :: 3 - Alpha
Classifier: Environment :: Web Environment
Classifier: Operating System :: OS Independent
Classifier: Topic :: Utilities
Classifier: Programming Language :: Python
Classifier: Topic :: Internet :: WWW/HTTP :: Dynamic Content
Classifier: License :: OSI Approved :: BSD License
